metaface/__init__.py
metaface/app/__init__.py
metaface/app/common.py
metaface/app/face_detection.py
metaface/app/face_detection_trt.py
metaface/app/face_recognition.py
metaface/app/face_recognition_trt.py
metaface/app/onnx_to_trt.py
metaface/app/persion_detection.py
metaface/model_zoo/__init__.py
metaface/model_zoo/arcface_onnx.py
metaface/model_zoo/arcface_trt.py
metaface/model_zoo/attribute.py
metaface/model_zoo/landmark.py
metaface/model_zoo/model_store.py
metaface/model_zoo/model_zoo.py
metaface/model_zoo/retinaface.py
metaface/model_zoo/retinaface_trt.py
metaface/model_zoo/scrfd.py
metaface/utils/__init__.py
metaface/utils/constant.py
metaface/utils/download.py
metaface/utils/face_align.py
metaface/utils/filesystem.py
metaface/utils/storage.py
metaface/utils/trt.py
meta_face-0.12.3.dist-info/METADATA
meta_face-0.12.3.dist-info/WHEEL
meta_face-0.12.3.dist-info/top_level.txt
meta_face-0.12.3.dist-info/zip-safe
meta_face-0.12.3.dist-info/RECORD
