Metadata-Version: 2.1
Name: meta-face
Version: 0.12.3
Summary: Meta Face Toolkit
Home-page: https://github.com/CachCheng/cvface
Author: CachCheng
Author-email: tkggpdc2007@163.com
License: Apache-2.0
Platform: UNKNOWN
Requires-Dist: numpy
Requires-Dist: requests
Requires-Dist: matplotlib
Requires-Dist: importlib-metadata
Requires-Dist: easydict
Requires-Dist: onnx
Requires-Dist: sklearn
Requires-Dist: cython
Requires-Dist: onnxruntime
Requires-Dist: opencv-python
Requires-Dist: tqdm
Requires-Dist: scikit-image
Requires-Dist: albumentations
